{
  "logoType": "none",
  "logo": {
    "lucideIcon": "",
    "imagePath": "",
    "imageLink": ""
  },
  "logoScale": 1.2,
  "iconColorType": "default",
  "wordmark": "",
  "customFont": "interfaceFont",
  "fontSize": "5em",
  "fontColorType": "default",
  "fontWeight": 600,
  "maxResults": 5,
  "showStarredFiles": false,
  "showRecentFiles": false,
  "maxRecentFiles": 5,
  "storeRecentFile": true,
  "showPath": true,
  "selectionHighlight": "default",
  "showShortcuts": true,
  "markdownOnly": false,
  "unresolvedLinks": false,
  "recentFilesStore": [
    {
      "filepath": "Stuff/Articles.md",
      "timestamp": 1739711005486
    },
    {
      "filepath": "Raw/Notes/Calico Routing Modes.md",
      "timestamp": 1739710979005
    },
    {
      "filepath": "Raw/Notes/Deep dive into Kubernetes network model and communication.md",
      "timestamp": 1739710233482
    },
    {
      "filepath": "Raw/Notes/Exploring the basics of Istio traffic management.md",
      "timestamp": 1739710160288
    }
  ],
  "starredFileStore": [],
  "searchDelay": 0,
  "replaceNewTabs": true,
  "newTabOnStart": false,
  "closePreviousSessionTabs": false,
  "omnisearch": false
}